tacotree/__init__.py
tacotree/_io.py
tacotree/_creation/__init__.py
tacotree/_creation/_config.py
tacotree/_creation/_creation_api.py
tacotree/_creation/_model.py
tacotree/_creation/_modules/__init__.py
tacotree/_creation/_modules/_base.py
tacotree/_creation/_modules/_m_axis_mod.py
tacotree/_creation/_modules/_m_global_pooling.py
tacotree/_creation/_modules/_m_in_out.py
tacotree/_creation/_modules/_m_math.py
tacotree/_creation/_modules/_m_misc.py
tacotree/_creation/_modules/_m_padding.py
tacotree/_creation/_modules/_pytorch_layer.py
tacotree/_creation/_modules/_sequential.py
tacotree/_creation/_modules/templates.py
tacotree/_datastructs/__init__.py
tacotree/_datastructs/_annotations.py
tacotree/_datastructs/_array.py
tacotree/_datastructs/_base_data.py
tacotree/_datastructs/_batch.py
tacotree/_datastructs/_sample.py
tacotree-1.0.0.dist-info/LICENSE
tacotree-1.0.0.dist-info/METADATA
tacotree-1.0.0.dist-info/WHEEL
tacotree-1.0.0.dist-info/top_level.txt
tacotree-1.0.0.dist-info/RECORD
