Metadata-Version: 2.1
Name: tacotree
Version: 1.0.0
Summary: Data processing pipelines based on PyTorch
Author: Matthias Nadig
Author-email: nadig_develop@yahoo.com
License: MIT
Requires-Python: >=3.7
License-File: LICENSE
Requires-Dist: tacotree-lab
Requires-Dist: numpy
Requires-Dist: ndbounds
Requires-Dist: torch
Requires-Dist: torchvision
